qernel/__init__.py
qernel/core/__init__.py
qernel/core/algorithm.py
qernel/core/client.py
qernel/core/plugin_loader.py
qernel/vis/__init__.py
qernel/vis/components.py
qernel/vis/templates.py
qernel/vis/visualizer.py
qernel/vis/html/__init__.py
qernel/vis/html/builder.py
qernel/vis/html/constants.py
qernel-0.0.1.dev0.dist-info/METADATA
qernel-0.0.1.dev0.dist-info/WHEEL
qernel-0.0.1.dev0.dist-info/top_level.txt
qernel-0.0.1.dev0.dist-info/RECORD
